{
  "project_info": {
    "project_number": "402131507290",
    "firebase_url": "https://meucampusv1.firebaseio.com",
    "project_id": "meucampusv1",
    "storage_bucket": "meucampusv1.appspot.com"
  },
  "client": [
    {
      "client_info": {
        "mobilesdk_app_id": "1:402131507290:android:83da162e83985be5",
        "android_client_info": {
          "package_name": "br.edu.ifmg.bambui.appmeucampus.meucampus"
        }
      },
      "oauth_client": [
        {
          "client_id": "402131507290-qttenud8qllnicg05vuiodqtm7m0ng0t.apps.googleusercontent.com",
          "client_type": 3
        }
      ],
      "api_key": [
        {
          "current_key": "AIzaSyCvtt_Vux770gAnWRt9R9PP0XO1DBR0icc"
        }
      ],
      "services": {
        "analytics_service": {
          "status": 1
        },
        "appinvite_service": {
          "status": 1,
          "other_platform_oauth_client": []
        },
        "ads_service": {
          "status": 2
        }
      }
    }
  ],
  "configuration_version": "1"
}